perfmetrics/__init__.py
perfmetrics/_metric.cpython-313-aarch64-linux-musl.so
perfmetrics/_metric.pxd
perfmetrics/_util.py
perfmetrics/clientstack.py
perfmetrics/interfaces.py
perfmetrics/metric.c
perfmetrics/metric.py
perfmetrics/pyramid.py
perfmetrics/statsd.py
perfmetrics/wsgi.py
perfmetrics/testing/__init__.py
perfmetrics/testing/client.py
perfmetrics/testing/matchers.py
perfmetrics/testing/observation.py
perfmetrics/testing/tests/__init__.py
perfmetrics/testing/tests/test_client.py
perfmetrics/testing/tests/test_matchers.py
perfmetrics/testing/tests/test_observation.py
perfmetrics/tests/__init__.py
perfmetrics/tests/bench_metric.py
perfmetrics/tests/test_clientstack.py
perfmetrics/tests/test_metric.py
perfmetrics/tests/test_perfmetrics.py
perfmetrics/tests/test_pyramid.py
perfmetrics/tests/test_statsd.py
perfmetrics/tests/test_wsgi.py
perfmetrics/tests/benchmarks/spraytest.py
perfmetrics-4.2.0.dist-info/METADATA
perfmetrics-4.2.0.dist-info/WHEEL
perfmetrics-4.2.0.dist-info/entry_points.txt
perfmetrics-4.2.0.dist-info/top_level.txt
perfmetrics-4.2.0.dist-info/zip-safe
perfmetrics-4.2.0.dist-info/RECORD
perfmetrics-4.2.0.dist-info/licenses/LICENSE.txt
