Metadata-Version: 2.4
Name: perfmetrics
Version: 4.2.0
Summary: Send performance metrics about Python code to Statsd
Home-page: https://github.com/zodb/perfmetrics
Author: Shane Hathaway
Author-email: shane@hathawaymix.org
Maintainer: Jason Madden
Maintainer-email: jason@seecoresoftware.com
License: BSD-derived (http://www.repoze.org/LICENSE.txt)
Project-URL: Bug Tracker, https://github.com/zodb/perfmetrics/issues
Project-URL: Source Code, https://github.com/zodb/perfmetrics/
Project-URL: Documentation, https://perfmetrics.readthedocs.io
Keywords: statsd metrics performance monitoring
Classifier: Development Status :: 5 - Production/Stable
Classifier: Intended Audience :: Developers
Classifier: Programming Language :: Python :: 3
Classifier: Programming Language :: Python :: 3 :: Only
Classifier: Programming Language :: Python :: 3.10
Classifier: Programming Language :: Python :: 3.11
Classifier: Programming Language :: Python :: 3.12
Classifier: Programming Language :: Python :: 3.13
Classifier: Programming Language :: Python :: 3.14
Classifier: Programming Language :: Python :: Implementation :: CPython
Classifier: Programming Language :: Python :: Implementation :: PyPy
Classifier: License :: Repoze Public License
Classifier: Topic :: System :: Monitoring
Requires-Python: >=3.10
License-File: LICENSE.txt
Requires-Dist: setuptools
Provides-Extra: test
Requires-Dist: zope.testrunner; extra == "test"
Requires-Dist: nti.testing; extra == "test"
Requires-Dist: zope.schema; extra == "test"
Requires-Dist: pyhamcrest>=1.10; extra == "test"
Requires-Dist: pyperf; extra == "test"
Provides-Extra: docs
Requires-Dist: Sphinx>=2.1.2; extra == "docs"
Requires-Dist: repoze.sphinx.autointerface; extra == "docs"
Requires-Dist: pyhamcrest; extra == "docs"
Requires-Dist: furo; extra == "docs"
Dynamic: author
Dynamic: author-email
Dynamic: classifier
Dynamic: description
Dynamic: home-page
Dynamic: keywords
Dynamic: license
Dynamic: license-file
Dynamic: maintainer
Dynamic: maintainer-email
Dynamic: project-url
Dynamic: provides-extra
Dynamic: requires-dist
Dynamic: requires-python
Dynamic: summary
